inovonics/cloud/oauth/__init__.py
inovonics/cloud/oauth/__version__.py
inovonics/cloud/oauth/handlers.py
inovonics/cloud/oauth/inooauth2provider.py
inovonics/cloud/oauth/datastore/__init__.py
inovonics/cloud/oauth/datastore/oauthclients.py
inovonics/cloud/oauth/datastore/oauthtokens.py
inovonics/cloud/oauth/datastore/oauthusers.py
inovonics_cloud_oauth-0.1.0.16.dist-info/DESCRIPTION.rst
inovonics_cloud_oauth-0.1.0.16.dist-info/METADATA
inovonics_cloud_oauth-0.1.0.16.dist-info/RECORD
inovonics_cloud_oauth-0.1.0.16.dist-info/WHEEL
inovonics_cloud_oauth-0.1.0.16.dist-info/metadata.json
inovonics_cloud_oauth-0.1.0.16.dist-info/top_level.txt
