Metadata-Version: 2.0
Name: inovonics-cloud-oauth
Version: 0.1.0.16
Summary: Classes implementing functionality for flask-oauthlib using Redis as the backing store.
Home-page: UNKNOWN
Author: Daniel Williams
Author-email: dwilliams@inovonics.com
License: MIT
Platform: UNKNOWN
Classifier: Development Status :: 4 - Beta
Classifier: Environment :: Web Environment
Classifier: Intended Audience :: Developers
Classifier: License :: OSI Approved
Classifier: License :: OSI Approved :: MIT License
Classifier: Operating System :: POSIX
Classifier: Operating System :: POSIX :: Linux
Classifier: Programming Language :: Python
Classifier: Programming Language :: Python :: 3.5
Classifier: Programming Language :: Python :: 3.6
Classifier: Topic :: Internet :: WWW/HTTP :: Dynamic Content
Classifier: Topic :: Software Development :: Libraries :: Python Modules
Requires-Dist: Flask (>=0.12)
Requires-Dist: Flask-OAuthlib (>=0.9.3)
Requires-Dist: inovonics-cloud-datastore (>=0.1.0.7)
Requires-Dist: passlib (>=1.7.1)
Requires-Dist: python-dateutil (>=2.5.3)
